langgraph_compare/__init__.py
langgraph_compare/analyze.py
langgraph_compare/analyze_case_id.py
langgraph_compare/artifacts.py
langgraph_compare/create_html.py
langgraph_compare/create_report.py
langgraph_compare/experiment.py
langgraph_compare/graph_runner.py
langgraph_compare/jsons_to_csv.py
langgraph_compare/load_events.py
langgraph_compare/sql_to_jsons.py
langgraph_compare/templates/comparison_report.html
langgraph_compare/templates/components/metrics.html
langgraph_compare/templates/components/modal.html
langgraph_compare/templates/components/scripts.html
langgraph_compare/templates/components/sequences.html
langgraph_compare/templates/components/styles.html
langgraph_compare/templates/components/visualizations.html
langgraph_compare/visualize.py
langgraph_compare-0.1.4.dist-info/LICENSE
langgraph_compare-0.1.4.dist-info/METADATA
langgraph_compare-0.1.4.dist-info/WHEEL
langgraph_compare-0.1.4.dist-info/RECORD
