Metadata-Version: 2.1
Name: langgraph-compare
Version: 0.1.4
Summary: Package for comparing and monitoring performance of LangGraph architectures.
Author: Tomasz Serafiński
Author-email: tomasz@serafinski.contact
Requires-Python: >=3.9,<4.0
Classifier: Programming Language :: Python :: 3
Classifier: Programming Language :: Python :: 3.9
Classifier: Programming Language :: Python :: 3.10
Classifier: Programming Language :: Python :: 3.11
Classifier: Programming Language :: Python :: 3.12
Classifier: Programming Language :: Python :: 3.13
Requires-Dist: jinja2 (>=3.1.2,<4.0.0)
Requires-Dist: langgraph (>=0.2.45,<0.3.0)
Requires-Dist: langgraph-checkpoint-sqlite (>=2.0.1,<3.0.0)
Requires-Dist: msgpack (>=1.1.0,<2.0.0)
Requires-Dist: pandas (>=2.2.3,<3.0.0)
Requires-Dist: pm4py (>=2.7.12.1,<3.0.0.0)
